tests/__init__.py
tests/test_auto_dtype.py
tests/test_build_pipeline.py
tests/test_clean_missing.py
tests/test_encode_categoricals.py
tests/test_feature_engineer.py
tests/test_handle_outliers.py
tests/test_scale_features.py
tests/test_suggest_pipeline.py
tidyflow/__init__.py
tidyflow/config.py
tidyflow/main.py
tidyflow/preprocessing/__init__.py
tidyflow/preprocessing/auto_dtype.py
tidyflow/preprocessing/build_pipeline.py
tidyflow/preprocessing/clean_missing.py
tidyflow/preprocessing/encode_categoricals.py
tidyflow/preprocessing/feature_engineer.py
tidyflow/preprocessing/handle_outliers.py
tidyflow/preprocessing/scale_features.py
tidyflow/preprocessing/suggest_pipeline.py
tidyflow/utils/__init__.py
tidyflow/utils/helpers.py
tidyflow/utils/logger.py
tidyflow-0.1.2.dist-info/METADATA
tidyflow-0.1.2.dist-info/WHEEL
tidyflow-0.1.2.dist-info/top_level.txt
tidyflow-0.1.2.dist-info/RECORD
