Metadata-Version: 2.1
Name: tidyflow
Version: 0.1.2
Summary: A lightweight data preprocessing toolbox
Home-page: https://github.com/AnnNaserNabil/tidyflow
Author: Ann Naser Nabil
Author-email: Ann Naser Nabil <ann.n.nabil@gmail.com>
License: MIT
Project-URL: Homepage, https://github.com/AnnNaserNabil/tidyflow
Requires-Python: >=3.8
Requires-Dist: pandas
Requires-Dist: numpy
Requires-Dist: scikit-learn
